rapids/__init__.py
rapids/config.py
rapids/decorators.py
rapids/documents.py
rapids/exceptions.py
rapids/openapi.py
rapids/raml.py
rapids/resources.py
rapids/utility.py
rapids-0.0.1.dist-info/DESCRIPTION.rst
rapids-0.0.1.dist-info/METADATA
rapids-0.0.1.dist-info/RECORD
rapids-0.0.1.dist-info/WHEEL
rapids-0.0.1.dist-info/metadata.json
rapids-0.0.1.dist-info/top_level.txt
