Metadata-Version: 2.0
Name: rapids
Version: 0.0.1
Summary: REST APIs documented and sensible
Home-page: https://github.com/sinoroc/rapids
Author: sinoroc
Author-email: sinoroc.code+python@gmail.com
License: Apache-2.0
Platform: UNKNOWN
Classifier: Framework :: Pyramid
Classifier: Intended Audience :: Developers
Classifier: License :: OSI Approved :: Apache Software License
Classifier: Programming Language :: Python
Classifier: Programming Language :: Python :: 3
Classifier: Programming Language :: Python :: 3.4
Classifier: Programming Language :: Python :: 3.5
Classifier: Programming Language :: Python :: 3.6
Classifier: Topic :: Internet :: WWW/HTTP
Classifier: Topic :: Software Development :: Libraries :: Application Frameworks
Classifier: Topic :: Software Development :: Libraries :: Python Modules
Requires-Dist: PyYAML
Requires-Dist: pyramid
Requires-Dist: setuptools
Requires-Dist: venusian
Requires-Dist: zope.interface
